README.rst
setup.py
pycached/__init__.py
pycached/_version.py
pycached/base.py
pycached/decorators.py
pycached/exceptions.py
pycached/factory.py
pycached/lock.py
pycached/plugins.py
pycached/serializers.py
pycached.egg-info/PKG-INFO
pycached.egg-info/SOURCES.txt
pycached.egg-info/dependency_links.txt
pycached.egg-info/requires.txt
pycached.egg-info/top_level.txt
pycached/backends/__init__.py
pycached/backends/memory.py
pycached/backends/redis.py
tests/__init__.py
tests/test_backkends.py
tests/test_base.py
tests/test_decorators.py
tests/test_factory.py
tests/ut/__init__.py
tests/ut/conftest.py
tests/ut/test_base.py
tests/ut/test_decorators.py
tests/ut/test_exceptions.py
tests/ut/test_factory.py
tests/ut/test_lock.py
tests/ut/test_plugins.py
tests/ut/test_serializers.py