Metadata-Version: 2.1
Name: pycached
Version: 0.0.9
Summary: multi backend cache
Home-page: https://github.com/fanjindong/pycached
Author: Fan Jindong
Author-email: 765912710@qq.com
License: UNKNOWN
Platform: UNKNOWN
Classifier: Programming Language :: Python
Classifier: Programming Language :: Python :: 3.5
Classifier: Programming Language :: Python :: 3.6
Classifier: Programming Language :: Python :: 3.7
Provides-Extra: redis"
Provides-Extra: msgpack
